app/__init__.py
app/adapters/__init__.py
app/adapters/blockcypher_adapters.py
app/adapters/sochain_adapters.py
app/controllers/__init__.py
app/controllers/addresses_controller.py
app/controllers/credentials_controller.py
app/controllers/setup_controller.py
app/controllers/status_controller.py
app/controllers/tx_controller.py
app/models/__init__.py
app/models/address_model.py
app/models/certificate_model.py
app/models/cluster_model.py
app/models/credentials_model.py
app/models/hsm_model.py
app/models/instance_model.py
app/models/pub_key_model.py
app/models/signed_tx_model.py
app/models/ssh_key_model.py
app/models/unsigned_tx_model.py
app/routes/__init__.py
app/routes/click.py
app/utilities/__init__.py
app/utilities/decorators.py
app/utilities/bitcoin/__init__.py
app/utilities/bitcoin/addresses.py
app/utilities/bitcoin/tx_scripts.py
app/utilities/ssh/__init__.py
app/utilities/ssh/install.sh
app/utilities/terraform/__init__.py
app/utilities/terraform/output.tf
app/utilities/terraform/step_1_vpc.tf
app/utilities/terraform/step_2_private_subnet.tf
app/utilities/terraform/step_3_create_a_cluster.tf
app/utilities/terraform/step_4_launch_an_EC2_client.tf
app/utilities/terraform/step_5_connect_EC2_instance_to_cluster.tf
app/utilities/terraform/varriables.tf
piggycli-0.0.35.dist-info/LICENSE
piggycli-0.0.35.dist-info/METADATA
piggycli-0.0.35.dist-info/WHEEL
piggycli-0.0.35.dist-info/entry_points.txt
piggycli-0.0.35.dist-info/top_level.txt
piggycli-0.0.35.dist-info/RECORD
